LICENSE
README.md
setup.py
speeddb/__init__.py
speeddb/browser.py
speeddb/cli.py
speeddb/database.py
speeddb/shell.py
speeddb/tasks_queue.py
speeddb.egg-info/PKG-INFO
speeddb.egg-info/SOURCES.txt
speeddb.egg-info/dependency_links.txt
speeddb.egg-info/entry_points.txt
speeddb.egg-info/not-zip-safe
speeddb.egg-info/requires.txt
speeddb.egg-info/top_level.txt