Metadata-Version: 2.1
Name: speeddb
Version: 1.0.1
Summary: SpeedDB
Home-page: https://github.com/SpeedDB/SpeedDB
Author: Nawaf Alqari
Author-email: nawafalqari13@gmail.com
License: MIT
Project-URL: Documentation, https://github.com/SpeedDB/SpeedDB#readme
Project-URL: Bug Tracker, https://github.com/SpeedDB/SpeedDB/issues
Project-URL: Source Code, https://github.com/SpeedDB/SpeedDB
Project-URL: Discord, https://discord.gg/cpvynqk4XT
Project-URL: Donate, https://paypal.me/NawafHAlqari
Keywords: speeddb,db,speed,fast,database
Platform: UNKNOWN
License-File: LICENSE
